astroscrappy-1.2.0.dist-info/METADATA
astroscrappy-1.2.0.dist-info/LICENSE.rst
astroscrappy-1.2.0.dist-info/RECORD
astroscrappy-1.2.0.dist-info/top_level.txt
astroscrappy-1.2.0.dist-info/WHEEL
astroscrappy.libs/libgomp-a34b3233.so.1.0.0
astroscrappy/_compiler.c
astroscrappy/astroscrappy.c
astroscrappy/astroscrappy.pyx
astroscrappy/setup_package.py
astroscrappy/version.py
astroscrappy/__init__.py
astroscrappy/astroscrappy.cpython-311-x86_64-linux-gnu.so
astroscrappy/compiler_version.cpython-311-x86_64-linux-gnu.so
astroscrappy/conftest.py
astroscrappy/utils/medutils.h
astroscrappy/utils/median_utils.pxd
astroscrappy/utils/setup_package.py
astroscrappy/utils/imutils.c
astroscrappy/utils/median_utils.pyx
astroscrappy/utils/image_utils.cpython-311-x86_64-linux-gnu.so
astroscrappy/utils/image_utils.pyx
astroscrappy/utils/__init__.py
astroscrappy/utils/medutils.c
astroscrappy/utils/median_utils.cpython-311-x86_64-linux-gnu.so
astroscrappy/utils/imutils.h
astroscrappy/tests/fake_data.py
astroscrappy/tests/test_gmos.py
astroscrappy/tests/test_cleaning.py
astroscrappy/tests/__init__.py
astroscrappy/tests/test_astroscrappy.py
astroscrappy/tests/test_utils.py
astroscrappy/tests/data/gmos.fits
