Metadata-Version: 2.1
Name: astroscrappy
Version: 1.2.0
Summary: Speedy Cosmic Ray Annihilation Package in Python
Author-email: Curtis McCully <cmccully@lco.global>
License: BSD-3-Clause
Project-URL: Homepage, https://github.com/astropy/astroscrappy
Requires-Python: >=3.9
License-File: licenses/LICENSE.rst
Requires-Dist: astropy
Requires-Dist: numpy
Provides-Extra: docs
Requires-Dist: sphinx-astropy ; extra == 'docs'
Provides-Extra: test
Requires-Dist: Cython ; extra == 'test'
Requires-Dist: pytest-astropy ; extra == 'test'
Requires-Dist: scipy ; extra == 'test'
